{
"appid":"569480",
"disqus":"app-569480",
"name":"Kingdoms and Castles",
"developer":"Lion Shield,LLC",
 "publisher":"Lion Shield,LLC",
 "localization":"ualt",
 "localization_released":"2018\/06\/20",
 "game_released":"20 лип 2017",
 "loc_desc":"<p>long description.<\/p><p>above:<\/p><p><\/p><ul><li>Тарас Mister Bond sda (sada, UaLT)\r\n<\/li><li>asdasd \r\n<\/li><li>asdasd\r\n<\/li><li>asda (asda)<\/li><\/ul><p><\/p>",
 "short_desc":"<p>Kingdoms and Castles.",
 "os_windows":"1",
 "os_linux":"1",
 "os_mac":"1",
 "is_f2p":"0",
 "img1_url":"https:\/\/imgur.com\/AM7Jok2.png",
 "img2_url":"https:\/\/imgur.com\/oenefD6.png",
 "img3_url":"https:\/\/imgur.com\/g2dsXxQ.png",
 "price_uah":"169",
 "download_url":"",
 "translate_url":"",
 "likes":"2"
 }
